{
  "updated_at": "2026-05-02T06:44:23+00:00",
  "working_on": {
    "feature": "forge",
    "task": "Forge 5.4.0 stable line and docs/current/* continuity",
    "status": "completed",
    "files": [
      "README.md",
      "docs/current/operator-surface.md",
      "packages/forge-skills/session-management/SKILL.md",
      "tests/test_context_contract_docs.py",
      "packages/forge-core/tests/test_session_context_boundaries.py",
      "docs/architecture/generated-host-artifacts/source-repo/operator-surface.md"
    ]
  },
  "pending_tasks": [
    "Resume the recorded workflow stage 'plan' before opening new scope."
  ],
  "recent_changes": [],
  "verification": [
    "python scripts/verify_repo.py: blocked before install by stale .brain/handover.md; refreshing tracked handover",
    "python -m unittest tests.test_context_contract_docs: OK",
    "python -m unittest test_session_context_boundaries: OK",
    "python -m unittest test_session_context: OK",
    "python -m unittest tests.test_host_artifact_generation tests.test_context_contract_docs: OK",
    "python scripts/verify_repo.py --profile fast: PASS"
  ],
  "decisions_made": [
    "Treat 5.4.0 as the current stable Forge release; docs/current/* remains the live maintainer source."
  ],
  "risks": [],
  "blockers": [],
  "source_artifacts": [
    "readme: C:\\Users\\Admin\\.gemini\\forge\\README.md",
    "plan: C:\\Users\\Admin\\.gemini\\forge\\docs\\plans\\2026-04-23-runtime-ownership-refactor-implementation-plan.md",
    "session: C:\\Users\\Admin\\.gemini\\forge\\.brain\\session.json",
    "handover: C:\\Users\\Admin\\.gemini\\forge\\.brain\\handover.md",
    "workflow-state: C:\\Users\\Admin\\.gemini\\forge\\.forge-artifacts\\workflow-state\\forge\\latest.json"
  ]
}
